{
    "HAND_SIZE": 3,
    "DEFAULT_BASE_WORKOUT":{
        "run": {
            "distance": 3000,
            "average_speed": 2.220,
            "time_3k": 1620,
            "time_5k": 2700,
            "time_10k": 5400
        },
        "ride": {
            "distance": 15000,
            "average_speed": 5.55,
            "time_40k": 7200
        },
        "walk": {
            "distance": 6000
        }
    },
    "ESTIMATION_ACCURACY": {
        "distance": 1000,
        "average_speed": 0.001
    },
    "UPDATABLE_PROPERTIES": [
        "time_3k",
        "time_5k",
        "time_10k",
        "time_40k"
    ],
    "QUEUE": {
        "LENGTH": 7,
        "CARDS_TO_SHIFT": 4
    },
    "CARD_VALUE_STEP": 5,
    "MAX_CARDS_SUBMIT": 1
}
